yors_pano_zero_field/__init__.py
yors_pano_zero_field/main.py
yors_pano_zero_field-1.0.0.dist-info/METADATA
yors_pano_zero_field-1.0.0.dist-info/WHEEL
yors_pano_zero_field-1.0.0.dist-info/RECORD
